{
  "metadata" : {
    "identifier" : "https://www.nettruyenio.com/truyen-tranh/bi-mat-cua-quy-co-680712",
    "title" : "Bí Mật Của Quý Cô - Chapter 31",
    "subtitle" : null,
    "author" : null,
    "narrator" : null,
    "language" : "vi",
    "description" : null,
    "publisher" : "N/A",
    "subject" : null,
    "modified" : null,
    "published" : "2023-08-18",
    "duration" : 0,
    "abridged" : false,
    "conformsTo" : "https://readium.org/webpub-manifest/profiles/divina",
    "numberOfPages" : 127,
    "readingProgression" : "ttb",
    "belongsTo" : null,
    "presentation" : {
      "fit" : "width",
      "overflow" : "scrolled",
      "continuous" : true
    },
    "@type" : null,
    "schema:license" : null
  },
  "links" : [ {
    "rel" : "self",
    "href" : "https://raw.githubusercontent.com/thuvienonline40/book_storage_collection/main/comic_manifest.json",
    "type" : "application/divina+json"
  } ],
  "readingOrder" : [ {
    "href" : "https://raw.githubusercontent.com/quetcccd/comic_storage6/main/IMAGE/IMAGE_d74fd0842e8831ed35cc56bbd79f2bf1_77fcf6853dfd89176e8396b8b30736b5_a6265f539c71ebd620146d81e9cb20cd.jpg",
    "type" : "image/jpeg",
    "bitrate" : 0,
    "duration" : 0,
    "title" : null,
    "properties" : null,
    "alternate" : [ {
      "href" : "https://i333.ntcdntempv3.com/data/images/68067/895515/001-ef1642c.jpg?data=net",
      "type" : "image/jpeg",
      "bitrate" : 0,
      "duration" : 0,
      "title" : null,
      "properties" : null,
      "alternate" : null
    } ]
  }, {
    "href" : "https://raw.githubusercontent.com/quetcccd/comic_storage6/main/IMAGE/IMAGE_d74fd0842e8831ed35cc56bbd79f2bf1_77fcf6853dfd89176e8396b8b30736b5_df699f91d897366539d30593c7787f63.jpg",
    "type" : "image/jpeg",
    "bitrate" : 0,
    "duration" : 0,
    "title" : null,
    "properties" : null,
    "alternate" : [ {
      "href" : "https://i333.ntcdntempv3.com/data/images/68067/895515/002-e4163c7.jpg?data=net",
      "type" : "image/jpeg",
      "bitrate" : 0,
      "duration" : 0,
      "title" : null,
      "properties" : null,
      "alternate" : null
    } ]
  }, {
    "href" : "https://raw.githubusercontent.com/quetcccd/comic_storage6/main/IMAGE/IMAGE_d74fd0842e8831ed35cc56bbd79f2bf1_77fcf6853dfd89176e8396b8b30736b5_4ad594e86ac8021e992a371076c9d49b.jpg",
    "type" : "image/jpeg",
    "bitrate" : 0,
    "duration" : 0,
    "title" : null,
    "properties" : null,
    "alternate" : [ {
      "href" : "https://i333.ntcdntempv3.com/data/images/68067/895515/003-79997c4.jpg?data=net",
      "type" : "image/jpeg",
      "bitrate" : 0,
      "duration" : 0,
      "title" : null,
      "properties" : null,
      "alternate" : null
    } ]
  }, {
    "href" : "https://raw.githubusercontent.com/quetcccd/comic_storage6/main/IMAGE/IMAGE_d74fd0842e8831ed35cc56bbd79f2bf1_77fcf6853dfd89176e8396b8b30736b5_8d3fc44484097d53746d864a890753ca.jpg",
    "type" : "image/jpeg",
    "bitrate" : 0,
    "duration" : 0,
    "title" : null,
    "properties" : null,
    "alternate" : [ {
      "href" : "https://i333.ntcdntempv3.com/data/images/68067/895515/004-67ef093.jpg?data=net",
      "type" : "image/jpeg",
      "bitrate" : 0,
      "duration" : 0,
      "title" : null,
      "properties" : null,
      "alternate" : null
    } ]
  }, {
    "href" : "https://raw.githubusercontent.com/quetcccd/comic_storage6/main/IMAGE/IMAGE_d74fd0842e8831ed35cc56bbd79f2bf1_77fcf6853dfd89176e8396b8b30736b5_f1db174db3adc879b7dc83b0c163c365.jpg",
    "type" : "image/jpeg",
    "bitrate" : 0,
    "duration" : 0,
    "title" : null,
    "properties" : null,
    "alternate" : [ {
      "href" : "https://i333.ntcdntempv3.com/data/images/68067/895515/005-966582e.jpg?data=net",
      "type" : "image/jpeg",
      "bitrate" : 0,
      "duration" : 0,
      "title" : null,
      "properties" : null,
      "alternate" : null
    } ]
  }, {
    "href" : "https://raw.githubusercontent.com/quetcccd/comic_storage6/main/IMAGE/IMAGE_d74fd0842e8831ed35cc56bbd79f2bf1_77fcf6853dfd89176e8396b8b30736b5_2d0d0dc1d03953da39943220602a6edb.jpg",
    "type" : "image/jpeg",
    "bitrate" : 0,
    "duration" : 0,
    "title" : null,
    "properties" : null,
    "alternate" : [ {
      "href" : "https://i333.ntcdntempv3.com/data/images/68067/895515/006-6790c4d.jpg?data=net",
      "type" : "image/jpeg",
      "bitrate" : 0,
      "duration" : 0,
      "title" : null,
      "properties" : null,
      "alternate" : null
    } ]
  }, {
    "href" : "https://raw.githubusercontent.com/quetcccd/comic_storage6/main/IMAGE/IMAGE_d74fd0842e8831ed35cc56bbd79f2bf1_77fcf6853dfd89176e8396b8b30736b5_fc6e05977c32a9831d7a5e6508e4f8c1.jpg",
    "type" : "image/jpeg",
    "bitrate" : 0,
    "duration" : 0,
    "title" : null,
    "properties" : null,
    "alternate" : [ {
      "href" : "https://i333.ntcdntempv3.com/data/images/68067/895515/007-afe82d2.jpg?data=net",
      "type" : "image/jpeg",
      "bitrate" : 0,
      "duration" : 0,
      "title" : null,
      "properties" : null,
      "alternate" : null
    } ]
  }, {
    "href" : "https://raw.githubusercontent.com/quetcccd/comic_storage6/main/IMAGE/IMAGE_d74fd0842e8831ed35cc56bbd79f2bf1_77fcf6853dfd89176e8396b8b30736b5_f6b017d920637a80065355f40f7cd17d.jpg",
    "type" : "image/jpeg",
    "bitrate" : 0,
    "duration" : 0,
    "title" : null,
    "properties" : null,
    "alternate" : [ {
      "href" : "https://i333.ntcdntempv3.com/data/images/68067/895515/008-4fad51d.jpg?data=net",
      "type" : "image/jpeg",
      "bitrate" : 0,
      "duration" : 0,
      "title" : null,
      "properties" : null,
      "alternate" : null
    } ]
  }, {
    "href" : "https://raw.githubusercontent.com/quetcccd/comic_storage6/main/IMAGE/IMAGE_d74fd0842e8831ed35cc56bbd79f2bf1_77fcf6853dfd89176e8396b8b30736b5_a2c7c71e005323d45381323efdebb9fd.jpg",
    "type" : "image/jpeg",
    "bitrate" : 0,
    "duration" : 0,
    "title" : null,
    "properties" : null,
    "alternate" : [ {
      "href" : "https://i333.ntcdntempv3.com/data/images/68067/895515/009-dbeb303.jpg?data=net",
      "type" : "image/jpeg",
      "bitrate" : 0,
      "duration" : 0,
      "title" : null,
      "properties" : null,
      "alternate" : null
    } ]
  }, {
    "href" : "https://raw.githubusercontent.com/quetcccd/comic_storage6/main/IMAGE/IMAGE_d74fd0842e8831ed35cc56bbd79f2bf1_77fcf6853dfd89176e8396b8b30736b5_f378869e1751e91d5b77f404550f502d.jpg",
    "type" : "image/jpeg",
    "bitrate" : 0,
    "duration" : 0,
    "title" : null,
    "properties" : null,
    "alternate" : [ {
      "href" : "https://i333.ntcdntempv3.com/data/images/68067/895515/010-ff6b709.jpg?data=net",
      "type" : "image/jpeg",
      "bitrate" : 0,
      "duration" : 0,
      "title" : null,
      "properties" : null,
      "alternate" : null
    } ]
  }, {
    "href" : "https://raw.githubusercontent.com/quetcccd/comic_storage6/main/IMAGE/IMAGE_d74fd0842e8831ed35cc56bbd79f2bf1_77fcf6853dfd89176e8396b8b30736b5_dd36424cb55266ba639c3d0fdc79d544.jpg",
    "type" : "image/jpeg",
    "bitrate" : 0,
    "duration" : 0,
    "title" : null,
    "properties" : null,
    "alternate" : [ {
      "href" : "https://i333.ntcdntempv3.com/data/images/68067/895515/011-bd59d35.jpg?data=net",
      "type" : "image/jpeg",
      "bitrate" : 0,
      "duration" : 0,
      "title" : null,
      "properties" : null,
      "alternate" : null
    } ]
  }, {
    "href" : "https://raw.githubusercontent.com/quetcccd/comic_storage6/main/IMAGE/IMAGE_d74fd0842e8831ed35cc56bbd79f2bf1_77fcf6853dfd89176e8396b8b30736b5_58e63b464c4694636a551eaa399f7cb0.jpg",
    "type" : "image/jpeg",
    "bitrate" : 0,
    "duration" : 0,
    "title" : null,
    "properties" : null,
    "alternate" : [ {
      "href" : "https://i333.ntcdntempv3.com/data/images/68067/895515/012-062d719.jpg?data=net",
      "type" : "image/jpeg",
      "bitrate" : 0,
      "duration" : 0,
      "title" : null,
      "properties" : null,
      "alternate" : null
    } ]
  }, {
    "href" : "https://raw.githubusercontent.com/quetcccd/comic_storage6/main/IMAGE/IMAGE_d74fd0842e8831ed35cc56bbd79f2bf1_77fcf6853dfd89176e8396b8b30736b5_c6aeed5e120c4456ee554d8202ee9716.jpg",
    "type" : "image/jpeg",
    "bitrate" : 0,
    "duration" : 0,
    "title" : null,
    "properties" : null,
    "alternate" : [ {
      "href" : "https://i333.ntcdntempv3.com/data/images/68067/895515/013-6b02cbb.jpg?data=net",
      "type" : "image/jpeg",
      "bitrate" : 0,
      "duration" : 0,
      "title" : null,
      "properties" : null,
      "alternate" : null
    } ]
  }, {
    "href" : "https://raw.githubusercontent.com/quetcccd/comic_storage6/main/IMAGE/IMAGE_d74fd0842e8831ed35cc56bbd79f2bf1_77fcf6853dfd89176e8396b8b30736b5_5b55755e4b5a8dbb19d0c5f83239ed7b.jpg",
    "type" : "image/jpeg",
    "bitrate" : 0,
    "duration" : 0,
    "title" : null,
    "properties" : null,
    "alternate" : [ {
      "href" : "https://i333.ntcdntempv3.com/data/images/68067/895515/014-6d1e2e5.jpg?data=net",
      "type" : "image/jpeg",
      "bitrate" : 0,
      "duration" : 0,
      "title" : null,
      "properties" : null,
      "alternate" : null
    } ]
  }, {
    "href" : "https://raw.githubusercontent.com/quetcccd/comic_storage6/main/IMAGE/IMAGE_d74fd0842e8831ed35cc56bbd79f2bf1_77fcf6853dfd89176e8396b8b30736b5_d400e37040bcc2e496e972f2e8f57ee6.jpg",
    "type" : "image/jpeg",
    "bitrate" : 0,
    "duration" : 0,
    "title" : null,
    "properties" : null,
    "alternate" : [ {
      "href" : "https://i333.ntcdntempv3.com/data/images/68067/895515/015-05ec366.jpg?data=net",
      "type" : "image/jpeg",
      "bitrate" : 0,
      "duration" : 0,
      "title" : null,
      "properties" : null,
      "alternate" : null
    } ]
  }, {
    "href" : "https://raw.githubusercontent.com/quetcccd/comic_storage6/main/IMAGE/IMAGE_d74fd0842e8831ed35cc56bbd79f2bf1_77fcf6853dfd89176e8396b8b30736b5_a9e2a15d095a91c872f0047d8652ed59.jpg",
    "type" : "image/jpeg",
    "bitrate" : 0,
    "duration" : 0,
    "title" : null,
    "properties" : null,
    "alternate" : [ {
      "href" : "https://i333.ntcdntempv3.com/data/images/68067/895515/016-992a08f.jpg?data=net",
      "type" : "image/jpeg",
      "bitrate" : 0,
      "duration" : 0,
      "title" : null,
      "properties" : null,
      "alternate" : null
    } ]
  }, {
    "href" : "https://raw.githubusercontent.com/quetcccd/comic_storage6/main/IMAGE/IMAGE_d74fd0842e8831ed35cc56bbd79f2bf1_77fcf6853dfd89176e8396b8b30736b5_fd9ab9a9c4263b82188664e3caa9f706.jpg",
    "type" : "image/jpeg",
    "bitrate" : 0,
    "duration" : 0,
    "title" : null,
    "properties" : null,
    "alternate" : [ {
      "href" : "https://i333.ntcdntempv3.com/data/images/68067/895515/017-c45d624.jpg?data=net",
      "type" : "image/jpeg",
      "bitrate" : 0,
      "duration" : 0,
      "title" : null,
      "properties" : null,
      "alternate" : null
    } ]
  }, {
    "href" : "https://raw.githubusercontent.com/quetcccd/comic_storage6/main/IMAGE/IMAGE_d74fd0842e8831ed35cc56bbd79f2bf1_77fcf6853dfd89176e8396b8b30736b5_59ee38d1d27e4a74a45dde32cc7c8030.jpg",
    "type" : "image/jpeg",
    "bitrate" : 0,
    "duration" : 0,
    "title" : null,
    "properties" : null,
    "alternate" : [ {
      "href" : "https://i333.ntcdntempv3.com/data/images/68067/895515/018-8ff3461.jpg?data=net",
      "type" : "image/jpeg",
      "bitrate" : 0,
      "duration" : 0,
      "title" : null,
      "properties" : null,
      "alternate" : null
    } ]
  }, {
    "href" : "https://raw.githubusercontent.com/quetcccd/comic_storage6/main/IMAGE/IMAGE_d74fd0842e8831ed35cc56bbd79f2bf1_77fcf6853dfd89176e8396b8b30736b5_50f2064b341baf827365fc01e76edffe.jpg",
    "type" : "image/jpeg",
    "bitrate" : 0,
    "duration" : 0,
    "title" : null,
    "properties" : null,
    "alternate" : [ {
      "href" : "https://i333.ntcdntempv3.com/data/images/68067/895515/019-eebae9f.jpg?data=net",
      "type" : "image/jpeg",
      "bitrate" : 0,
      "duration" : 0,
      "title" : null,
      "properties" : null,
      "alternate" : null
    } ]
  }, {
    "href" : "https://raw.githubusercontent.com/quetcccd/comic_storage6/main/IMAGE/IMAGE_d74fd0842e8831ed35cc56bbd79f2bf1_77fcf6853dfd89176e8396b8b30736b5_a2450d77bb3ec8cc764b325471a836cf.jpg",
    "type" : "image/jpeg",
    "bitrate" : 0,
    "duration" : 0,
    "title" : null,
    "properties" : null,
    "alternate" : [ {
      "href" : "https://i333.ntcdntempv3.com/data/images/68067/895515/020-eb9c160.jpg?data=net",
      "type" : "image/jpeg",
      "bitrate" : 0,
      "duration" : 0,
      "title" : null,
      "properties" : null,
      "alternate" : null
    } ]
  }, {
    "href" : "https://raw.githubusercontent.com/quetcccd/comic_storage6/main/IMAGE/IMAGE_d74fd0842e8831ed35cc56bbd79f2bf1_77fcf6853dfd89176e8396b8b30736b5_41dfeca09a7096c8ec59e1188a2e437c.jpg",
    "type" : "image/jpeg",
    "bitrate" : 0,
    "duration" : 0,
    "title" : null,
    "properties" : null,
    "alternate" : [ {
      "href" : "https://i333.ntcdntempv3.com/data/images/68067/895515/021-0dd098a.jpg?data=net",
      "type" : "image/jpeg",
      "bitrate" : 0,
      "duration" : 0,
      "title" : null,
      "properties" : null,
      "alternate" : null
    } ]
  }, {
    "href" : "https://raw.githubusercontent.com/quetcccd/comic_storage6/main/IMAGE/IMAGE_d74fd0842e8831ed35cc56bbd79f2bf1_77fcf6853dfd89176e8396b8b30736b5_cc41db8a210d34272084299afbdabf4d.jpg",
    "type" : "image/jpeg",
    "bitrate" : 0,
    "duration" : 0,
    "title" : null,
    "properties" : null,
    "alternate" : [ {
      "href" : "https://i333.ntcdntempv3.com/data/images/68067/895515/022-e6e2bdf.jpg?data=net",
      "type" : "image/jpeg",
      "bitrate" : 0,
      "duration" : 0,
      "title" : null,
      "properties" : null,
      "alternate" : null
    } ]
  }, {
    "href" : "https://raw.githubusercontent.com/quetcccd/comic_storage6/main/IMAGE/IMAGE_d74fd0842e8831ed35cc56bbd79f2bf1_77fcf6853dfd89176e8396b8b30736b5_73c9836078189e7c61948fa2d251b4f3.jpg",
    "type" : "image/jpeg",
    "bitrate" : 0,
    "duration" : 0,
    "title" : null,
    "properties" : null,
    "alternate" : [ {
      "href" : "https://i333.ntcdntempv3.com/data/images/68067/895515/023-9c04e94.jpg?data=net",
      "type" : "image/jpeg",
      "bitrate" : 0,
      "duration" : 0,
      "title" : null,
      "properties" : null,
      "alternate" : null
    } ]
  }, {
    "href" : "https://raw.githubusercontent.com/quetcccd/comic_storage6/main/IMAGE/IMAGE_d74fd0842e8831ed35cc56bbd79f2bf1_77fcf6853dfd89176e8396b8b30736b5_f278d19d9228902b40d715e1773f6705.jpg",
    "type" : "image/jpeg",
    "bitrate" : 0,
    "duration" : 0,
    "title" : null,
    "properties" : null,
    "alternate" : [ {
      "href" : "https://i333.ntcdntempv3.com/data/images/68067/895515/024-c414e53.jpg?data=net",
      "type" : "image/jpeg",
      "bitrate" : 0,
      "duration" : 0,
      "title" : null,
      "properties" : null,
      "alternate" : null
    } ]
  } ],
  "toc" : null,
  "@context" : "https://readium.org/webpub-manifest/context.jsonld"
}